hush_engine/__init__.py
hush_engine/analyze_feedback.py
hush_engine/detection_config.py
hush_engine/rpc_server.py
hush_engine/scrub_image.py
hush_engine/scrub_spreadsheet.py
hush_engine/anonymizers/__init__.py
hush_engine/anonymizers/image_anonymizer.py
hush_engine/anonymizers/spreadsheet_anonymizer.py
hush_engine/detectors/__init__.py
hush_engine/detectors/pii_detector.py
hush_engine/ocr/__init__.py
hush_engine/ocr/vision_ocr.py
hush_engine/pdf/__init__.py
hush_engine/pdf/pdf_processor.py
hush_engine/ui/__init__.py
hush_engine/ui/file_router.py
hush_engine-1.0.2.dist-info/licenses/LICENSE
hush_engine-1.0.2.dist-info/METADATA
hush_engine-1.0.2.dist-info/WHEEL
hush_engine-1.0.2.dist-info/top_level.txt
hush_engine-1.0.2.dist-info/RECORD
