Metadata-Version: 2.4
Name: hush-engine
Version: 1.0.2
Summary: Local-first PII detection engine using Presidio and Apple Vision OCR
Author-email: Valentine Makhouleen <valentine@newmediastudio.com>
License: MIT
Project-URL: Homepage, https://github.com/NewMediaStudio/hush-engine
Project-URL: Repository, https://github.com/NewMediaStudio/hush-engine
Project-URL: Issues, https://github.com/NewMediaStudio/hush-engine/issues
Keywords: pii,privacy,detection,ocr,presidio,anonymization,data-security
Classifier: Development Status :: 4 - Beta
Classifier: Intended Audience :: Developers
Classifier: License :: OSI Approved :: MIT License
Classifier: Programming Language :: Python :: 3.10
Classifier: Programming Language :: Python :: 3.11
Classifier: Programming Language :: Python :: 3.12
Classifier: Topic :: Security
Classifier: Topic :: Software Development :: Libraries :: Python Modules
Classifier: Operating System :: MacOS :: MacOS X
Requires-Python: >=3.10
License-File: LICENSE
Requires-Dist: presidio-analyzer>=2.2.0
Requires-Dist: presidio-anonymizer>=2.2.0
Requires-Dist: Pillow>=10.0.0
Requires-Dist: pdf2image>=1.17.0
Requires-Dist: img2pdf>=0.6.3
Requires-Dist: pandas>=2.0.0
Requires-Dist: openpyxl>=3.1.0
Requires-Dist: spacy>=3.7.0
Requires-Dist: faker>=20.0.0
Requires-Dist: pyobjc-framework-Vision>=9.0
Requires-Dist: pyobjc-framework-Cocoa>=9.0
Requires-Dist: watchdog>=3.0.0
Dynamic: license-file
